ptsd/__init__.py
ptsd/ast.py
ptsd/constants.py
ptsd/lexer.py
ptsd/loader.py
ptsd/parser.py
ptsd_jbroll/__init__.py
ptsd_jbroll/ast.py
ptsd_jbroll/constants.py
ptsd_jbroll/lexer.py
ptsd_jbroll/loader.py
ptsd_jbroll/parser.py
ptsd_jbroll-0.2.2.data/scripts/ptsd
ptsd_jbroll-0.2.2.dist-info/LICENSE
ptsd_jbroll-0.2.2.dist-info/METADATA
ptsd_jbroll-0.2.2.dist-info/WHEEL
ptsd_jbroll-0.2.2.dist-info/top_level.txt
ptsd_jbroll-0.2.2.dist-info/zip-safe
ptsd_jbroll-0.2.2.dist-info/RECORD
