Metadata-Version: 2.1
Name: ptsd-jbroll
Version: 0.2.2
Summary: python thrift simple/dumb
Home-page: http://github.com/jbroll/ptsd
Author: John Roll
Author-email: john@rkroll.com
License: MIT
Platform: UNKNOWN
Requires-Dist: ply
